CLUEstering/CLUEstering.py
CLUEstering/__init__.py
CLUEstering-1.1.4.dist-info/LICENSE
CLUEstering-1.1.4.dist-info/METADATA
CLUEstering-1.1.4.dist-info/WHEEL
CLUEstering-1.1.4.dist-info/top_level.txt
CLUEstering-1.1.4.dist-info/RECORD
